Workbook

Sheet Cover
A1: TestCo Industries — DCF Valuation
A3: Color legend
A4: Blue text | B4: hardcoded input (Assumptions only)
A5: Black text | B5: formula
A6: Green text | B6: cross-sheet link
A7: Yellow background | B7: key cells / CMP / 20% IRR row
A9: VALUATION SUMMARY
A10: Metric | B10: Bear | C10: Base | D10: Bull
A11: Revenue (FY35) | B11: ='DCF'!$M$7 | C11: ='DCF'!$M$8 | D11: ='DCF'!$M$9
A12: EBITDA (FY35) | B12: ='DCF'!$M$21 | C12: ='DCF'!$M$24 | D12: ='DCF'!$M$27
A13: FCFF (FY35) | B13: ='DCF'!$M$42 | C13: ='DCF'!$M$57 | D13: ='DCF'!$M$72
A14: Sum PV(FCFFs) | B14: ='DCF'!$B$89 | C14: ='DCF'!$C$89 | D14: ='DCF'!$D$89
A15: Terminal Value | B15: ='DCF'!$B$91 | C15: ='DCF'!$C$91 | D15: ='DCF'!$D$91
A16: Enterprise Value | B16: ='DCF'!$B$93 | C16: ='DCF'!$C$93 | D16: ='DCF'!$D$93
A17: Equity Value | B17: ='DCF'!$B$95 | C17: ='DCF'!$C$95 | D17: ='DCF'!$D$95
A18: Implied Price per Share | B18: ='DCF'!$B$97 | C18: ='DCF'!$C$97 | D18: ='DCF'!$D$97
A19: CMP | B19: ='Assumptions'!$B$8 | C19: ='Assumptions'!$B$8 | D19: ='Assumptions'!$B$8
A20: Upside vs CMP | B20: ='DCF'!$B$99 | C20: ='DCF'!$C$99 | D20: ='DCF'!$D$99
A22: KEY OBSERVATIONS
A23: • Base case implies modest upside vs CMP; high sensitivity to WACC
A24: • Multiple-based exit yields wider range vs DCF intrinsic
A25: • Reverse DCF: implied TGR exceeds Base — market pricing in stronger growth
A27: ESTIMATED INPUTS (flagged)
A28: • beta: ESTIMATED — basis: 2y weekly regression on Yahoo data

Sheet Assumptions
A1: ASSUMPTIONS — TestCo Industries
A3: COMPANY
A4: Company name | B4: TestCo Industries
A5: Ticker | B5: TESTCO.NS
A6: Currency | B6: INR
A7: FY end | B7: Mar
A8: Current Market Price (CMP) | B8: 1500
A9: Diluted shares outstanding (mn) | B9: 100
A10: Net cash (Cash − Debt) | B10: -5000
A12: WACC BUILD
A13: Component | B13: Value | H13: Source / Rationale
A14: Risk-free rate (Rf, 10y govt bond) | B14: 0.071 | H14: Rf: 10y G-Sec; ERP: Damodaran India Jul-26
A15: Equity risk premium (ERP, Damodaran) | B15: 0.075
A16: Beta (2y weekly vs benchmark) | B16: 1.1
A17: Cost of equity (Ke = Rf + β × ERP) | B17: =B14+B16*B15
A18: Cost of debt (Kd, pre-tax) | B18: 0.085
A19: Tax rate | B19: 0.252
A20: Kd after-tax = Kd × (1 − T) | B20: =B18*(1-B19)
A21: Equity weight | B21: 0.85
A22: Debt weight = 1 − Equity weight | B22: =1-B21
A23: WACC = Ke × wₑ + Kd_AT × w_d | B23: =B17*B21+B20*B22
A25: SCENARIO ASSUMPTIONS
A26: Driver | B26: Bear | C26: Base | D26: Bull | H26: Rationale
A27: Revenue CAGR Phase 1 (FY26–FY30) | B27: 0.07 | C27: 0.12 | D27: 0.18 | H27: Mgmt guidance: revenue 12-14% CAGR
A28: Revenue CAGR Phase 2 (FY31–FY35) | B28: 0.04 | C28: 0.07 | D28: 0.1
A29: EBITDA margin (terminal year) | B29: 0.16 | C29: 0.2 | D29: 0.24
A30: Tax rate (steady-state) | B30: 0.252 | C30: 0.252 | D30: 0.252
A31: Capex % of revenue | B31: 0.045 | C31: 0.04 | D31: 0.038
A32: D&A % of revenue | B32: 0.03 | C32: 0.03 | D32: 0.03
A33: ΔNWC % of revenue | B33: 0.02 | C33: 0.02 | D33: 0.02
A34: Terminal growth rate (TGR) | B34: 0.03 | C34: 0.04 | D34: 0.05
A36: HISTORICAL ACTUALS
A37: Line item | B37: FY23 | C37: FY24 | H37: Source
A38: Revenue | B38: 50000 | C38: 58000
A39: EBITDA | B39: 9000 | C39: 11000
A40: D&A | B40: 1500 | C40: 1700
A41: Capex | B41: 2200 | C41: 2400
A42: ΔNWC | B42: 800 | C42: 950
A43: Effective tax rate | B43: 0.252 | C43: 0.248
A45: PEER COMPS
A46: Peer | B46: EV/NTM Rev | C46: NTM Rev CAGR | D46: NTM EBITDA Margin | E46: EV/NTM EBITDA
A47: Peer A | B47: 4.2 | C47: 0.14 | D47: 0.22 | E47: 19
A48: Peer B | B48: 3.5 | C48: 0.1 | D48: 0.18 | E48: 16.5
A49: Peer C | B49: 5.1 | C49: 0.18 | D49: 0.25 | E49: 21
A50: Peer D | B50: 2.8 | C50: 0.08 | D50: 0.16 | E50: 14
A51: Mean | B51: =AVERAGE(B47:B50) | C51: =AVERAGE(C47:C50) | D51: =AVERAGE(D47:D50) | E51: =AVERAGE(E47:E50)
A52: Median | B52: =MEDIAN(B47:B50) | C52: =MEDIAN(C47:C50) | D52: =MEDIAN(D47:D50) | E52: =MEDIAN(E47:E50)
A54: EXIT MULTIPLE
A55: Multiple type | B55: EV/EBITDA | H55: Mature profitable cash-flow generator → EBITDA multiple
A56: Metric year | B56: FY30
A57: Exit multiple | B57: Bear | C57: Base | D57: Bull
A58: multiple (x) | B58: 12 | C58: 17 | D58: 22
A60: ESTIMATED INPUTS (flagged)
A61: • beta: ESTIMATED — basis: 2y weekly regression on Yahoo data

Sheet DCF
A1: DCF MODEL — TestCo Industries
A3: § 1 REVENUE BUILD
A4: Year | B4: FY23A | C4: FY24A | D4: FY26E | E4: FY27E | F4: FY28E | G4: FY29E | H4: FY30E | I4: FY31E | J4: FY32E | K4: FY33E | L4: FY34E | M4: FY35E
A5: Revenue (historical) | B5: ='Assumptions'!$B$38 | C5: ='Assumptions'!$C$38
A7: Revenue — Bear | B7: =B5 | C7: =C5 | D7: =C7*(1+'Assumptions'!$B$27) | E7: =D7*(1+'Assumptions'!$B$27) | F7: =E7*(1+'Assumptions'!$B$27) | G7: =F7*(1+'Assumptions'!$B$27) | H7: =G7*(1+'Assumptions'!$B$27) | I7: =H7*(1+'Assumptions'!$B$28) | J7: =I7*(1+'Assumptions'!$B$28) | K7: =J7*(1+'Assumptions'!$B$28) | L7: =K7*(1+'Assumptions'!$B$28) | M7: =L7*(1+'Assumptions'!$B$28)
A8: Revenue — Base | B8: =B5 | C8: =C5 | D8: =C8*(1+'Assumptions'!$C$27) | E8: =D8*(1+'Assumptions'!$C$27) | F8: =E8*(1+'Assumptions'!$C$27) | G8: =F8*(1+'Assumptions'!$C$27) | H8: =G8*(1+'Assumptions'!$C$27) | I8: =H8*(1+'Assumptions'!$C$28) | J8: =I8*(1+'Assumptions'!$C$28) | K8: =J8*(1+'Assumptions'!$C$28) | L8: =K8*(1+'Assumptions'!$C$28) | M8: =L8*(1+'Assumptions'!$C$28)
A9: Revenue — Bull | B9: =B5 | C9: =C5 | D9: =C9*(1+'Assumptions'!$D$27) | E9: =D9*(1+'Assumptions'!$D$27) | F9: =E9*(1+'Assumptions'!$D$27) | G9: =F9*(1+'Assumptions'!$D$27) | H9: =G9*(1+'Assumptions'!$D$27) | I9: =H9*(1+'Assumptions'!$D$28) | J9: =I9*(1+'Assumptions'!$D$28) | K9: =J9*(1+'Assumptions'!$D$28) | L9: =K9*(1+'Assumptions'!$D$28) | M9: =L9*(1+'Assumptions'!$D$28)
A11: growth % — Bear | D11: =D7/C7-1 | E11: =E7/D7-1 | F11: =F7/E7-1 | G11: =G7/F7-1 | H11: =H7/G7-1 | I11: =I7/H7-1 | J11: =J7/I7-1 | K11: =K7/J7-1 | ... M11: =M7/L7-1
A12: growth % — Base | D12: =D8/C8-1 | E12: =E8/D8-1 | F12: =F8/E8-1 | G12: =G8/F8-1 | H12: =H8/G8-1 | I12: =I8/H8-1 | J12: =J8/I8-1 | K12: =K8/J8-1 | ... M12: =M8/L8-1
A13: growth % — Bull | D13: =D9/C9-1 | E13: =E9/D9-1 | F13: =F9/E9-1 | G13: =G9/F9-1 | H13: =H9/G9-1 | I13: =I9/H9-1 | J13: =J9/I9-1 | K13: =K9/J9-1 | ... M13: =M9/L9-1
A15: § 2 EBITDA & COST WATERFALL
A16: Year | B16: FY23A | C16: FY24A | D16: FY26E | E16: FY27E | F16: FY28E | G16: FY29E | H16: FY30E | I16: FY31E | J16: FY32E | K16: FY33E | L16: FY34E | M16: FY35E
A17: EBITDA (historical) | B17: ='Assumptions'!$B$39 | C17: ='Assumptions'!$C$39
A18: EBITDA margin (historical) | B18: =B17/B5 | C18: =C17/C5
A20: EBITDA margin — Bear | B20: =B17/B5 | C20: =C17/C5 | D20: =C20+('Assumptions'!$B$29-C20)*1/10 | E20: =C20+('Assumptions'!$B$29-C20)*2/10 | F20: =C20+('Assumptions'!$B$29-C20)*3/10 | G20: =C20+('Assumptions'!$B$29-C20)*4/10 | H20: =C20+('Assumptions'!$B$29-C20)*5/10 | I20: =C20+('Assumptions'!$B$29-C20)*6/10 | J20: =C20+('Assumptions'!$B$29-C20)*7/10 | K20: =C20+('Assumptions'!$B$29-C20)*8/10 | L20: =C20+('Assumptions'!$B$29-C20)*9/10 | M20: =C20+('Assumptions'!$B$29-C20)*10/10
A21: EBITDA — Bear | B21: =B17 | C21: =C17 | D21: =D7*D20 | E21: =E7*E20 | F21: =F7*F20 | G21: =G7*G20 | H21: =H7*H20 | I21: =I7*I20 | J21: =J7*J20 | K21: =K7*K20 | ... M21: =M7*M20
A23: EBITDA margin — Base | B23: =B17/B5 | C23: =C17/C5 | D23: =C23+('Assumptions'!$C$29-C23)*1/10 | E23: =C23+('Assumptions'!$C$29-C23)*2/10 | F23: =C23+('Assumptions'!$C$29-C23)*3/10 | G23: =C23+('Assumptions'!$C$29-C23)*4/10 | H23: =C23+('Assumptions'!$C$29-C23)*5/10 | I23: =C23+('Assumptions'!$C$29-C23)*6/10 | J23: =C23+('Assumptions'!$C$29-C23)*7/10 | K23: =C23+('Assumptions'!$C$29-C23)*8/10 | L23: =C23+('Assumptions'!$C$29-C23)*9/10 | M23: =C23+('Assumptions'!$C$29-C23)*10/10
A24: EBITDA — Base | B24: =B17 | C24: =C17 | D24: =D8*D23 | E24: =E8*E23 | F24: =F8*F23 | G24: =G8*G23 | H24: =H8*H23 | I24: =I8*I23 | J24: =J8*J23 | K24: =K8*K23 | ... M24: =M8*M23
A26: EBITDA margin — Bull | B26: =B17/B5 | C26: =C17/C5 | D26: =C26+('Assumptions'!$D$29-C26)*1/10 | E26: =C26+('Assumptions'!$D$29-C26)*2/10 | F26: =C26+('Assumptions'!$D$29-C26)*3/10 | G26: =C26+('Assumptions'!$D$29-C26)*4/10 | H26: =C26+('Assumptions'!$D$29-C26)*5/10 | I26: =C26+('Assumptions'!$D$29-C26)*6/10 | J26: =C26+('Assumptions'!$D$29-C26)*7/10 | K26: =C26+('Assumptions'!$D$29-C26)*8/10 | L26: =C26+('Assumptions'!$D$29-C26)*9/10 | M26: =C26+('Assumptions'!$D$29-C26)*10/10
A27: EBITDA — Bull | B27: =B17 | C27: =C17 | D27: =D9*D26 | E27: =E9*E26 | F27: =F9*F26 | G27: =G9*G26 | H27: =H9*H26 | I27: =I9*I26 | J27: =J9*J26 | K27: =K9*K26 | ... M27: =M9*M26
A30: § 3 FCFF BRIDGE (per scenario)
A31: ▸ BEAR CASE
A32: Year | B32: FY23A | C32: FY24A | D32: FY26E | E32: FY27E | F32: FY28E | G32: FY29E | H32: FY30E | I32: FY31E | J32: FY32E | K32: FY33E | L32: FY34E | M32: FY35E
A33: Year # | B33: — | C33: — | D33: 1 | E33: 2 | F33: 3 | G33: 4 | H33: 5 | I33: 6 | J33: 7 | K33: 8 | L33: 9 | M33: 10
A34: EBITDA | B34: =B21 | C34: =C21 | D34: =D21 | E34: =E21 | F34: =F21 | G34: =G21 | H34: =H21 | I34: =I21 | ... M34: =M21
A35: − D&A | B35: =-'Assumptions'!$B$40 | C35: =-'Assumptions'!$C$40 | D35: =-D7*'Assumptions'!$B$32 | E35: =-E7*'Assumptions'!$B$32 | F35: =-F7*'Assumptions'!$B$32 | G35: =-G7*'Assumptions'!$B$32 | H35: =-H7*'Assumptions'!$B$32 | I35: =-I7*'Assumptions'!$B$32 | J35: =-J7*'Assumptions'!$B$32 | K35: =-K7*'Assumptions'!$B$32 | ... M35: =-M7*'Assumptions'!$B$32
A36: EBIT | B36: =B34+B35 | C36: =C34+C35 | D36: =D34+D35 | E36: =E34+E35 | F36: =F34+F35 | G36: =G34+G35 | H36: =H34+H35 | I36: =I34+I35 | ... M36: =M34+M35
A37: − Tax | B37: =-B36*'Assumptions'!$B$43 | C37: =-C36*'Assumptions'!$C$43 | D37: =-MAX(D36,0)*'Assumptions'!$B$30 | E37: =-MAX(E36,0)*'Assumptions'!$B$30 | F37: =-MAX(F36,0)*'Assumptions'!$B$30 | G37: =-MAX(G36,0)*'Assumptions'!$B$30 | H37: =-MAX(H36,0)*'Assumptions'!$B$30 | I37: =-MAX(I36,0)*'Assumptions'!$B$30 | J37: =-MAX(J36,0)*'Assumptions'!$B$30 | K37: =-MAX(K36,0)*'Assumptions'!$B$30 | ... M37: =-MAX(M36,0)*'Assumptions'!$B$30
A38: NOPAT | B38: =B36+B37 | C38: =C36+C37 | D38: =D36+D37 | E38: =E36+E37 | F38: =F36+F37 | G38: =G36+G37 | H38: =H36+H37 | I38: =I36+I37 | ... M38: =M36+M37
A39: + D&A (add back) | B39: =-B35 | C39: =-C35 | D39: =-D35 | E39: =-E35 | F39: =-F35 | G39: =-G35 | H39: =-H35 | I39: =-I35 | ... M39: =-M35
A40: − Capex | B40: =-'Assumptions'!$B$41 | C40: =-'Assumptions'!$C$41 | D40: =-D7*'Assumptions'!$B$31 | E40: =-E7*'Assumptions'!$B$31 | F40: =-F7*'Assumptions'!$B$31 | G40: =-G7*'Assumptions'!$B$31 | H40: =-H7*'Assumptions'!$B$31 | I40: =-I7*'Assumptions'!$B$31 | J40: =-J7*'Assumptions'!$B$31 | K40: =-K7*'Assumptions'!$B$31 | ... M40: =-M7*'Assumptions'!$B$31
A41: − ΔNWC | B41: =-'Assumptions'!$B$42 | C41: =-'Assumptions'!$C$42 | D41: =-D7*'Assumptions'!$B$33 | E41: =-E7*'Assumptions'!$B$33 | F41: =-F7*'Assumptions'!$B$33 | G41: =-G7*'Assumptions'!$B$33 | H41: =-H7*'Assumptions'!$B$33 | I41: =-I7*'Assumptions'!$B$33 | J41: =-J7*'Assumptions'!$B$33 | K41: =-K7*'Assumptions'!$B$33 | ... M41: =-M7*'Assumptions'!$B$33
A42: FCFF | B42: =B38+B39+B40+B41 | C42: =C38+C39+C40+C41 | D42: =D38+D39+D40+D41 | E42: =E38+E39+E40+E41 | F42: =F38+F39+F40+F41 | G42: =G38+G39+G40+G41 | H42: =H38+H39+H40+H41 | I42: =I38+I39+I40+I41 | ... M42: =M38+M39+M40+M41
A43: Discount factor | B43: — | C43: — | D43: =1/((1+'Assumptions'!$B$23)^D33) | E43: =1/((1+'Assumptions'!$B$23)^E33) | F43: =1/((1+'Assumptions'!$B$23)^F33) | G43: =1/((1+'Assumptions'!$B$23)^G33) | H43: =1/((1+'Assumptions'!$B$23)^H33) | I43: =1/((1+'Assumptions'!$B$23)^I33) | J43: =1/((1+'Assumptions'!$B$23)^J33) | K43: =1/((1+'Assumptions'!$B$23)^K33) | ... M43: =1/((1+'Assumptions'!$B$23)^M33)
A44: PV of FCFF | B44: — | C44: — | D44: =D42*D43 | E44: =E42*E43 | F44: =F42*F43 | G44: =G42*G43 | H44: =H42*H43 | I44: =I42*I43 | J44: =J42*J43 | K44: =K42*K43 | ... M44: =M42*M43
A46: ▸ BASE CASE
A47: Year | B47: FY23A | C47: FY24A | D47: FY26E | E47: FY27E | F47: FY28E | G47: FY29E | H47: FY30E | I47: FY31E | J47: FY32E | K47: FY33E | L47: FY34E | M47: FY35E
A48: Year # | B48: — | C48: — | D48: 1 | E48: 2 | F48: 3 | G48: 4 | H48: 5 | I48: 6 | J48: 7 | K48: 8 | L48: 9 | M48: 10
A49: EBITDA | B49: =B24 | C49: =C24 | D49: =D24 | E49: =E24 | F49: =F24 | G49: =G24 | H49: =H24 | I49: =I24 | ... M49: =M24
A50: − D&A | B50: =-'Assumptions'!$B$40 | C50: =-'Assumptions'!$C$40 | D50: =-D8*'Assumptions'!$C$32 | E50: =-E8*'Assumptions'!$C$32 | F50: =-F8*'Assumptions'!$C$32 | G50: =-G8*'Assumptions'!$C$32 | H50: =-H8*'Assumptions'!$C$32 | I50: =-I8*'Assumptions'!$C$32 | J50: =-J8*'Assumptions'!$C$32 | K50: =-K8*'Assumptions'!$C$32 | ... M50: =-M8*'Assumptions'!$C$32
A51: EBIT | B51: =B49+B50 | C51: =C49+C50 | D51: =D49+D50 | E51: =E49+E50 | F51: =F49+F50 | G51: =G49+G50 | H51: =H49+H50 | I51: =I49+I50 | ... M51: =M49+M50
A52: − Tax | B52: =-B51*'Assumptions'!$B$43 | C52: =-C51*'Assumptions'!$C$43 | D52: =-MAX(D51,0)*'Assumptions'!$C$30 | E52: =-MAX(E51,0)*'Assumptions'!$C$30 | F52: =-MAX(F51,0)*'Assumptions'!$C$30 | G52: =-MAX(G51,0)*'Assumptions'!$C$30 | H52: =-MAX(H51,0)*'Assumptions'!$C$30 | I52: =-MAX(I51,0)*'Assumptions'!$C$30 | J52: =-MAX(J51,0)*'Assumptions'!$C$30 | K52: =-MAX(K51,0)*'Assumptions'!$C$30 | ... M52: =-MAX(M51,0)*'Assumptions'!$C$30
A53: NOPAT | B53: =B51+B52 | C53: =C51+C52 | D53: =D51+D52 | E53: =E51+E52 | F53: =F51+F52 | G53: =G51+G52 | H53: =H51+H52 | I53: =I51+I52 | ... M53: =M51+M52
A54: + D&A (add back) | B54: =-B50 | C54: =-C50 | D54: =-D50 | E54: =-E50 | F54: =-F50 | G54: =-G50 | H54: =-H50 | I54: =-I50 | ... M54: =-M50
A55: − Capex | B55: =-'Assumptions'!$B$41 | C55: =-'Assumptions'!$C$41 | D55: =-D8*'Assumptions'!$C$31 | E55: =-E8*'Assumptions'!$C$31 | F55: =-F8*'Assumptions'!$C$31 | G55: =-G8*'Assumptions'!$C$31 | H55: =-H8*'Assumptions'!$C$31 | I55: =-I8*'Assumptions'!$C$31 | J55: =-J8*'Assumptions'!$C$31 | K55: =-K8*'Assumptions'!$C$31 | ... M55: =-M8*'Assumptions'!$C$31
A56: − ΔNWC | B56: =-'Assumptions'!$B$42 | C56: =-'Assumptions'!$C$42 | D56: =-D8*'Assumptions'!$C$33 | E56: =-E8*'Assumptions'!$C$33 | F56: =-F8*'Assumptions'!$C$33 | G56: =-G8*'Assumptions'!$C$33 | H56: =-H8*'Assumptions'!$C$33 | I56: =-I8*'Assumptions'!$C$33 | J56: =-J8*'Assumptions'!$C$33 | K56: =-K8*'Assumptions'!$C$33 | ... M56: =-M8*'Assumptions'!$C$33
A57: FCFF | B57: =B53+B54+B55+B56 | C57: =C53+C54+C55+C56 | D57: =D53+D54+D55+D56 | E57: =E53+E54+E55+E56 | F57: =F53+F54+F55+F56 | G57: =G53+G54+G55+G56 | H57: =H53+H54+H55+H56 | I57: =I53+I54+I55+I56 | ... M57: =M53+M54+M55+M56
A58: Discount factor | B58: — | C58: — | D58: =1/((1+'Assumptions'!$B$23)^D48) | E58: =1/((1+'Assumptions'!$B$23)^E48) | F58: =1/((1+'Assumptions'!$B$23)^F48) | G58: =1/((1+'Assumptions'!$B$23)^G48) | H58: =1/((1+'Assumptions'!$B$23)^H48) | I58: =1/((1+'Assumptions'!$B$23)^I48) | J58: =1/((1+'Assumptions'!$B$23)^J48) | K58: =1/((1+'Assumptions'!$B$23)^K48) | ... M58: =1/((1+'Assumptions'!$B$23)^M48)
A59: PV of FCFF | B59: — | C59: — | D59: =D57*D58 | E59: =E57*E58 | F59: =F57*F58 | G59: =G57*G58 | H59: =H57*H58 | I59: =I57*I58 | J59: =J57*J58 | K59: =K57*K58 | ... M59: =M57*M58
A61: ▸ BULL CASE
A62: Year | B62: FY23A | C62: FY24A | D62: FY26E | E62: FY27E | F62: FY28E | G62: FY29E | H62: FY30E | I62: FY31E | J62: FY32E | K62: FY33E | L62: FY34E | M62: FY35E
A63: Year # | B63: — | C63: — | D63: 1 | E63: 2 | F63: 3 | G63: 4 | H63: 5 | I63: 6 | J63: 7 | K63: 8 | L63: 9 | M63: 10
A64: EBITDA | B64: =B27 | C64: =C27 | D64: =D27 | E64: =E27 | F64: =F27 | G64: =G27 | H64: =H27 | I64: =I27 | ... M64: =M27
A65: − D&A | B65: =-'Assumptions'!$B$40 | C65: =-'Assumptions'!$C$40 | D65: =-D9*'Assumptions'!$D$32 | E65: =-E9*'Assumptions'!$D$32 | F65: =-F9*'Assumptions'!$D$32 | G65: =-G9*'Assumptions'!$D$32 | H65: =-H9*'Assumptions'!$D$32 | I65: =-I9*'Assumptions'!$D$32 | J65: =-J9*'Assumptions'!$D$32 | K65: =-K9*'Assumptions'!$D$32 | ... M65: =-M9*'Assumptions'!$D$32
A66: EBIT | B66: =B64+B65 | C66: =C64+C65 | D66: =D64+D65 | E66: =E64+E65 | F66: =F64+F65 | G66: =G64+G65 | H66: =H64+H65 | I66: =I64+I65 | ... M66: =M64+M65
A67: − Tax | B67: =-B66*'Assumptions'!$B$43 | C67: =-C66*'Assumptions'!$C$43 | D67: =-MAX(D66,0)*'Assumptions'!$D$30 | E67: =-MAX(E66,0)*'Assumptions'!$D$30 | F67: =-MAX(F66,0)*'Assumptions'!$D$30 | G67: =-MAX(G66,0)*'Assumptions'!$D$30 | H67: =-MAX(H66,0)*'Assumptions'!$D$30 | I67: =-MAX(I66,0)*'Assumptions'!$D$30 | J67: =-MAX(J66,0)*'Assumptions'!$D$30 | K67: =-MAX(K66,0)*'Assumptions'!$D$30 | ... M67: =-MAX(M66,0)*'Assumptions'!$D$30
A68: NOPAT | B68: =B66+B67 | C68: =C66+C67 | D68: =D66+D67 | E68: =E66+E67 | F68: =F66+F67 | G68: =G66+G67 | H68: =H66+H67 | I68: =I66+I67 | ... M68: =M66+M67
A69: + D&A (add back) | B69: =-B65 | C69: =-C65 | D69: =-D65 | E69: =-E65 | F69: =-F65 | G69: =-G65 | H69: =-H65 | I69: =-I65 | ... M69: =-M65
A70: − Capex | B70: =-'Assumptions'!$B$41 | C70: =-'Assumptions'!$C$41 | D70: =-D9*'Assumptions'!$D$31 | E70: =-E9*'Assumptions'!$D$31 | F70: =-F9*'Assumptions'!$D$31 | G70: =-G9*'Assumptions'!$D$31 | H70: =-H9*'Assumptions'!$D$31 | I70: =-I9*'Assumptions'!$D$31 | J70: =-J9*'Assumptions'!$D$31 | K70: =-K9*'Assumptions'!$D$31 | ... M70: =-M9*'Assumptions'!$D$31
A71: − ΔNWC | B71: =-'Assumptions'!$B$42 | C71: =-'Assumptions'!$C$42 | D71: =-D9*'Assumptions'!$D$33 | E71: =-E9*'Assumptions'!$D$33 | F71: =-F9*'Assumptions'!$D$33 | G71: =-G9*'Assumptions'!$D$33 | H71: =-H9*'Assumptions'!$D$33 | I71: =-I9*'Assumptions'!$D$33 | J71: =-J9*'Assumptions'!$D$33 | K71: =-K9*'Assumptions'!$D$33 | ... M71: =-M9*'Assumptions'!$D$33
A72: FCFF | B72: =B68+B69+B70+B71 | C72: =C68+C69+C70+C71 | D72: =D68+D69+D70+D71 | E72: =E68+E69+E70+E71 | F72: =F68+F69+F70+F71 | G72: =G68+G69+G70+G71 | H72: =H68+H69+H70+H71 | I72: =I68+I69+I70+I71 | ... M72: =M68+M69+M70+M71
A73: Discount factor | B73: — | C73: — | D73: =1/((1+'Assumptions'!$B$23)^D63) | E73: =1/((1+'Assumptions'!$B$23)^E63) | F73: =1/((1+'Assumptions'!$B$23)^F63) | G73: =1/((1+'Assumptions'!$B$23)^G63) | H73: =1/((1+'Assumptions'!$B$23)^H63) | I73: =1/((1+'Assumptions'!$B$23)^I63) | J73: =1/((1+'Assumptions'!$B$23)^J63) | K73: =1/((1+'Assumptions'!$B$23)^K63) | ... M73: =1/((1+'Assumptions'!$B$23)^M63)
A74: PV of FCFF | B74: — | C74: — | D74: =D72*D73 | E74: =E72*E73 | F74: =F72*F73 | G74: =G72*G73 | H74: =H72*H73 | I74: =I72*I73 | J74: =J72*J73 | K74: =K72*K73 | ... M74: =M72*M73
A77: § 4 WACC SUMMARY (linked from Assumptions)
A78: Risk-free rate (Rf) | B78: ='Assumptions'!$B$14
A79: ERP | B79: ='Assumptions'!$B$15
A80: Beta | B80: ='Assumptions'!$B$16
A81: Cost of equity (Ke) | B81: ='Assumptions'!$B$17
A82: Cost of debt after-tax (Kd_AT) | B82: ='Assumptions'!$B$20
A83: Equity weight | B83: ='Assumptions'!$B$21
A84: Debt weight | B84: ='Assumptions'!$B$22
A85: WACC | B85: ='Assumptions'!$B$23
A87: § 5 VALUATION (Bear / Base / Bull)
A88: Line item | B88: Bear | C88: Base | D88: Bull
A89: Sum PV(FCFFs) — explicit forecast | B89: =SUM(D44:M44) | C89: =SUM(D59:M59) | D89: =SUM(D74:M74)
A90: Terminal FCFF (Year N × (1+TGR)) | B90: =M42*(1+'Assumptions'!$B$34) | C90: =M57*(1+'Assumptions'!$C$34) | D90: =M72*(1+'Assumptions'!$D$34)
A91: Terminal Value (GGM) | B91: =B90/('Assumptions'!$B$23-'Assumptions'!$B$34) | C91: =C90/('Assumptions'!$B$23-'Assumptions'!$C$34) | D91: =D90/('Assumptions'!$B$23-'Assumptions'!$D$34)
A92: PV of Terminal Value | B92: =B91/((1+'Assumptions'!$B$23)^10) | C92: =C91/((1+'Assumptions'!$B$23)^10) | D92: =D91/((1+'Assumptions'!$B$23)^10)
A93: Enterprise Value | B93: =B89+B92 | C93: =C89+C92 | D93: =D89+D92
A94: + Net Cash (− Net Debt) | B94: ='Assumptions'!$B$10 | C94: ='Assumptions'!$B$10 | D94: ='Assumptions'!$B$10
A95: Equity Value | B95: =B93+B94 | C95: =C93+C94 | D95: =D93+D94
A96: ÷ Diluted shares (mn) | B96: ='Assumptions'!$B$9 | C96: ='Assumptions'!$B$9 | D96: ='Assumptions'!$B$9
A97: Implied Price per Share | B97: =B95/'Assumptions'!$B$9 | C97: =C95/'Assumptions'!$B$9 | D97: =D95/'Assumptions'!$B$9
A98: CMP | B98: ='Assumptions'!$B$8 | C98: ='Assumptions'!$B$8 | D98: ='Assumptions'!$B$8
A99: Upside vs CMP | B99: =B97/'Assumptions'!$B$8-1 | C99: =C97/'Assumptions'!$B$8-1 | D99: =D97/'Assumptions'!$B$8-1
A102: § 6 SENSITIVITY — Implied price (Base, GGM)
A103: WACC ↓ / TGR → | B103: ='Assumptions'!$C$34+(-0.01) | C103: ='Assumptions'!$C$34+(-0.005) | D103: ='Assumptions'!$C$34+(0.0) | E103: ='Assumptions'!$C$34+(0.005) | F103: ='Assumptions'!$C$34+(0.01)
A104: ='Assumptions'!$B$23+(-0.01) | B104: =(SUMPRODUCT(D57:M57/(1+$A$104)^D48:M48)+M57*(1+$B$103)/($A$104-$B$103)/(1+$A$104)^10+'Assumptions'!$B$10)/'Assumptions'!$B$9 | C104: =(SUMPRODUCT(D57:M57/(1+$A$104)^D48:M48)+M57*(1+$C$103)/($A$104-$C$103)/(1+$A$104)^10+'Assumptions'!$B$10)/'Assumptions'!$B$9 | D104: =(SUMPRODUCT(D57:M57/(1+$A$104)^D48:M48)+M57*(1+$D$103)/($A$104-$D$103)/(1+$A$104)^10+'Assumptions'!$B$10)/'Assumptions'!$B$9 | E104: =(SUMPRODUCT(D57:M57/(1+$A$104)^D48:M48)+M57*(1+$E$103)/($A$104-$E$103)/(1+$A$104)^10+'Assumptions'!$B$10)/'Assumptions'!$B$9 | F104: =(SUMPRODUCT(D57:M57/(1+$A$104)^D48:M48)+M57*(1+$F$103)/($A$104-$F$103)/(1+$A$104)^10+'Assumptions'!$B$10)/'Assumptions'!$B$9
A105: ='Assumptions'!$B$23+(-0.005) | B105: =(SUMPRODUCT(D57:M57/(1+$A$105)^D48:M48)+M57*(1+$B$103)/($A$105-$B$103)/(1+$A$105)^10+'Assumptions'!$B$10)/'Assumptions'!$B$9 | C105: =(SUMPRODUCT(D57:M57/(1+$A$105)^D48:M48)+M57*(1+$C$103)/($A$105-$C$103)/(1+$A$105)^10+'Assumptions'!$B$10)/'Assumptions'!$B$9 | D105: =(SUMPRODUCT(D57:M57/(1+$A$105)^D48:M48)+M57*(1+$D$103)/($A$105-$D$103)/(1+$A$105)^10+'Assumptions'!$B$10)/'Assumptions'!$B$9 | E105: =(SUMPRODUCT(D57:M57/(1+$A$105)^D48:M48)+M57*(1+$E$103)/($A$105-$E$103)/(1+$A$105)^10+'Assumptions'!$B$10)/'Assumptions'!$B$9 | F105: =(SUMPRODUCT(D57:M57/(1+$A$105)^D48:M48)+M57*(1+$F$103)/($A$105-$F$103)/(1+$A$105)^10+'Assumptions'!$B$10)/'Assumptions'!$B$9
A106: ='Assumptions'!$B$23+(0.0) | B106: =(SUMPRODUCT(D57:M57/(1+$A$106)^D48:M48)+M57*(1+$B$103)/($A$106-$B$103)/(1+$A$106)^10+'Assumptions'!$B$10)/'Assumptions'!$B$9 | C106: =(SUMPRODUCT(D57:M57/(1+$A$106)^D48:M48)+M57*(1+$C$103)/($A$106-$C$103)/(1+$A$106)^10+'Assumptions'!$B$10)/'Assumptions'!$B$9 | D106: =(SUMPRODUCT(D57:M57/(1+$A$106)^D48:M48)+M57*(1+$D$103)/($A$106-$D$103)/(1+$A$106)^10+'Assumptions'!$B$10)/'Assumptions'!$B$9 | E106: =(SUMPRODUCT(D57:M57/(1+$A$106)^D48:M48)+M57*(1+$E$103)/($A$106-$E$103)/(1+$A$106)^10+'Assumptions'!$B$10)/'Assumptions'!$B$9 | F106: =(SUMPRODUCT(D57:M57/(1+$A$106)^D48:M48)+M57*(1+$F$103)/($A$106-$F$103)/(1+$A$106)^10+'Assumptions'!$B$10)/'Assumptions'!$B$9
A107: ='Assumptions'!$B$23+(0.005) | B107: =(SUMPRODUCT(D57:M57/(1+$A$107)^D48:M48)+M57*(1+$B$103)/($A$107-$B$103)/(1+$A$107)^10+'Assumptions'!$B$10)/'Assumptions'!$B$9 | C107: =(SUMPRODUCT(D57:M57/(1+$A$107)^D48:M48)+M57*(1+$C$103)/($A$107-$C$103)/(1+$A$107)^10+'Assumptions'!$B$10)/'Assumptions'!$B$9 | D107: =(SUMPRODUCT(D57:M57/(1+$A$107)^D48:M48)+M57*(1+$D$103)/($A$107-$D$103)/(1+$A$107)^10+'Assumptions'!$B$10)/'Assumptions'!$B$9 | E107: =(SUMPRODUCT(D57:M57/(1+$A$107)^D48:M48)+M57*(1+$E$103)/($A$107-$E$103)/(1+$A$107)^10+'Assumptions'!$B$10)/'Assumptions'!$B$9 | F107: =(SUMPRODUCT(D57:M57/(1+$A$107)^D48:M48)+M57*(1+$F$103)/($A$107-$F$103)/(1+$A$107)^10+'Assumptions'!$B$10)/'Assumptions'!$B$9
A108: ='Assumptions'!$B$23+(0.01) | B108: =(SUMPRODUCT(D57:M57/(1+$A$108)^D48:M48)+M57*(1+$B$103)/($A$108-$B$103)/(1+$A$108)^10+'Assumptions'!$B$10)/'Assumptions'!$B$9 | C108: =(SUMPRODUCT(D57:M57/(1+$A$108)^D48:M48)+M57*(1+$C$103)/($A$108-$C$103)/(1+$A$108)^10+'Assumptions'!$B$10)/'Assumptions'!$B$9 | D108: =(SUMPRODUCT(D57:M57/(1+$A$108)^D48:M48)+M57*(1+$D$103)/($A$108-$D$103)/(1+$A$108)^10+'Assumptions'!$B$10)/'Assumptions'!$B$9 | E108: =(SUMPRODUCT(D57:M57/(1+$A$108)^D48:M48)+M57*(1+$E$103)/($A$108-$E$103)/(1+$A$108)^10+'Assumptions'!$B$10)/'Assumptions'!$B$9 | F108: =(SUMPRODUCT(D57:M57/(1+$A$108)^D48:M48)+M57*(1+$F$103)/($A$108-$F$103)/(1+$A$108)^10+'Assumptions'!$B$10)/'Assumptions'!$B$9
A111: § 7 REVERSE DCF — what is CMP implying?
A112: Implied Equity Value at CMP | B112: ='Assumptions'!$B$8*'Assumptions'!$B$9
A113: Implied Enterprise Value at CMP | B113: =B112-'Assumptions'!$B$10
A114: DCF EV (Base scenario) | B114: =C93
A115: Gap (Implied − DCF) | B115: =B113-B114
A117: Implied TGR at CMP (holding Base FCFFs & WACC fixed) | B117: =((B113-C89)*(1+'Assumptions'!$B$23)^10*'Assumptions'!$B$23-M57)/((B113-C89)*(1+'Assumptions'!$B$23)^10+M57)
A118: Implied terminal FCFF at CMP (assuming Base TGR) | B118: =(B113-C89)*(1+'Assumptions'!$B$23)^10*('Assumptions'!$B$23-'Assumptions'!$C$34)/(1+'Assumptions'!$C$34)
A119: vs Base scenario terminal FCFF (explicit) | B119: =C90

Sheet Returns_DCF
A1: RETURNS — DCF Intrinsic (exit = DCF intrinsic value only)
A3: Approach: A — DCF Intrinsic
A4: Exit prices from DCF intrinsic value only; no market multiple applied.
A6: ▸ BEAR CASE
A7: Entry price ↓ / Holding period → | B7: 3 yr | C7: 5 yr | D7: 7 yr | E7: 10 yr | F7: Exit price (DCF intrinsic)
A8: ='Assumptions'!$B$8*(1+-0.3) | B8: =('DCF'!$B$97/A8)^(1/3)-1 | C8: =('DCF'!$B$97/A8)^(1/5)-1 | D8: =('DCF'!$B$97/A8)^(1/7)-1 | E8: =('DCF'!$B$97/A8)^(1/10)-1 | F8: ='DCF'!$B$97
A9: ='Assumptions'!$B$8*(1+-0.2) | B9: =('DCF'!$B$97/A9)^(1/3)-1 | C9: =('DCF'!$B$97/A9)^(1/5)-1 | D9: =('DCF'!$B$97/A9)^(1/7)-1 | E9: =('DCF'!$B$97/A9)^(1/10)-1 | F9: ='DCF'!$B$97
A10: ='Assumptions'!$B$8*(1+-0.1) | B10: =('DCF'!$B$97/A10)^(1/3)-1 | C10: =('DCF'!$B$97/A10)^(1/5)-1 | D10: =('DCF'!$B$97/A10)^(1/7)-1 | E10: =('DCF'!$B$97/A10)^(1/10)-1 | F10: ='DCF'!$B$97
A11: ='Assumptions'!$B$8*(1+0.0) | B11: =('DCF'!$B$97/A11)^(1/3)-1 | C11: =('DCF'!$B$97/A11)^(1/5)-1 | D11: =('DCF'!$B$97/A11)^(1/7)-1 | E11: =('DCF'!$B$97/A11)^(1/10)-1 | F11: ='DCF'!$B$97
A12: ='Assumptions'!$B$8*(1+0.1) | B12: =('DCF'!$B$97/A12)^(1/3)-1 | C12: =('DCF'!$B$97/A12)^(1/5)-1 | D12: =('DCF'!$B$97/A12)^(1/7)-1 | E12: =('DCF'!$B$97/A12)^(1/10)-1 | F12: ='DCF'!$B$97
A13: ='Assumptions'!$B$8*(1+0.2) | B13: =('DCF'!$B$97/A13)^(1/3)-1 | C13: =('DCF'!$B$97/A13)^(1/5)-1 | D13: =('DCF'!$B$97/A13)^(1/7)-1 | E13: =('DCF'!$B$97/A13)^(1/10)-1 | F13: ='DCF'!$B$97
A14: ='Assumptions'!$B$8*(1+0.3) | B14: =('DCF'!$B$97/A14)^(1/3)-1 | C14: =('DCF'!$B$97/A14)^(1/5)-1 | D14: =('DCF'!$B$97/A14)^(1/7)-1 | E14: =('DCF'!$B$97/A14)^(1/10)-1 | F14: ='DCF'!$B$97
A16: Max entry for target IRR | B16: 3 yr | C16: 5 yr | D16: 7 yr | E16: 10 yr
A17: 10% IRR target | B17: ='DCF'!$B$97/(1+0.1)^3 | C17: ='DCF'!$B$97/(1+0.1)^5 | D17: ='DCF'!$B$97/(1+0.1)^7 | E17: ='DCF'!$B$97/(1+0.1)^10
A18: 15% IRR target | B18: ='DCF'!$B$97/(1+0.15)^3 | C18: ='DCF'!$B$97/(1+0.15)^5 | D18: ='DCF'!$B$97/(1+0.15)^7 | E18: ='DCF'!$B$97/(1+0.15)^10
A19: 20% IRR target | B19: ='DCF'!$B$97/(1+0.2)^3 | C19: ='DCF'!$B$97/(1+0.2)^5 | D19: ='DCF'!$B$97/(1+0.2)^7 | E19: ='DCF'!$B$97/(1+0.2)^10
A20: 25% IRR target | B20: ='DCF'!$B$97/(1+0.25)^3 | C20: ='DCF'!$B$97/(1+0.25)^5 | D20: ='DCF'!$B$97/(1+0.25)^7 | E20: ='DCF'!$B$97/(1+0.25)^10
A21: 30% IRR target | B21: ='DCF'!$B$97/(1+0.3)^3 | C21: ='DCF'!$B$97/(1+0.3)^5 | D21: ='DCF'!$B$97/(1+0.3)^7 | E21: ='DCF'!$B$97/(1+0.3)^10
A24: ▸ BASE CASE
A25: Entry price ↓ / Holding period → | B25: 3 yr | C25: 5 yr | D25: 7 yr | E25: 10 yr | F25: Exit price (DCF intrinsic)
A26: ='Assumptions'!$B$8*(1+-0.3) | B26: =('DCF'!$C$97/A26)^(1/3)-1 | C26: =('DCF'!$C$97/A26)^(1/5)-1 | D26: =('DCF'!$C$97/A26)^(1/7)-1 | E26: =('DCF'!$C$97/A26)^(1/10)-1 | F26: ='DCF'!$C$97
A27: ='Assumptions'!$B$8*(1+-0.2) | B27: =('DCF'!$C$97/A27)^(1/3)-1 | C27: =('DCF'!$C$97/A27)^(1/5)-1 | D27: =('DCF'!$C$97/A27)^(1/7)-1 | E27: =('DCF'!$C$97/A27)^(1/10)-1 | F27: ='DCF'!$C$97
A28: ='Assumptions'!$B$8*(1+-0.1) | B28: =('DCF'!$C$97/A28)^(1/3)-1 | C28: =('DCF'!$C$97/A28)^(1/5)-1 | D28: =('DCF'!$C$97/A28)^(1/7)-1 | E28: =('DCF'!$C$97/A28)^(1/10)-1 | F28: ='DCF'!$C$97
A29: ='Assumptions'!$B$8*(1+0.0) | B29: =('DCF'!$C$97/A29)^(1/3)-1 | C29: =('DCF'!$C$97/A29)^(1/5)-1 | D29: =('DCF'!$C$97/A29)^(1/7)-1 | E29: =('DCF'!$C$97/A29)^(1/10)-1 | F29: ='DCF'!$C$97
A30: ='Assumptions'!$B$8*(1+0.1) | B30: =('DCF'!$C$97/A30)^(1/3)-1 | C30: =('DCF'!$C$97/A30)^(1/5)-1 | D30: =('DCF'!$C$97/A30)^(1/7)-1 | E30: =('DCF'!$C$97/A30)^(1/10)-1 | F30: ='DCF'!$C$97
A31: ='Assumptions'!$B$8*(1+0.2) | B31: =('DCF'!$C$97/A31)^(1/3)-1 | C31: =('DCF'!$C$97/A31)^(1/5)-1 | D31: =('DCF'!$C$97/A31)^(1/7)-1 | E31: =('DCF'!$C$97/A31)^(1/10)-1 | F31: ='DCF'!$C$97
A32: ='Assumptions'!$B$8*(1+0.3) | B32: =('DCF'!$C$97/A32)^(1/3)-1 | C32: =('DCF'!$C$97/A32)^(1/5)-1 | D32: =('DCF'!$C$97/A32)^(1/7)-1 | E32: =('DCF'!$C$97/A32)^(1/10)-1 | F32: ='DCF'!$C$97
A34: Max entry for target IRR | B34: 3 yr | C34: 5 yr | D34: 7 yr | E34: 10 yr
A35: 10% IRR target | B35: ='DCF'!$C$97/(1+0.1)^3 | C35: ='DCF'!$C$97/(1+0.1)^5 | D35: ='DCF'!$C$97/(1+0.1)^7 | E35: ='DCF'!$C$97/(1+0.1)^10
A36: 15% IRR target | B36: ='DCF'!$C$97/(1+0.15)^3 | C36: ='DCF'!$C$97/(1+0.15)^5 | D36: ='DCF'!$C$97/(1+0.15)^7 | E36: ='DCF'!$C$97/(1+0.15)^10
A37: 20% IRR target | B37: ='DCF'!$C$97/(1+0.2)^3 | C37: ='DCF'!$C$97/(1+0.2)^5 | D37: ='DCF'!$C$97/(1+0.2)^7 | E37: ='DCF'!$C$97/(1+0.2)^10
A38: 25% IRR target | B38: ='DCF'!$C$97/(1+0.25)^3 | C38: ='DCF'!$C$97/(1+0.25)^5 | D38: ='DCF'!$C$97/(1+0.25)^7 | E38: ='DCF'!$C$97/(1+0.25)^10
A39: 30% IRR target | B39: ='DCF'!$C$97/(1+0.3)^3 | C39: ='DCF'!$C$97/(1+0.3)^5 | D39: ='DCF'!$C$97/(1+0.3)^7 | E39: ='DCF'!$C$97/(1+0.3)^10
A42: ▸ BULL CASE
A43: Entry price ↓ / Holding period → | B43: 3 yr | C43: 5 yr | D43: 7 yr | E43: 10 yr | F43: Exit price (DCF intrinsic)
A44: ='Assumptions'!$B$8*(1+-0.3) | B44: =('DCF'!$D$97/A44)^(1/3)-1 | C44: =('DCF'!$D$97/A44)^(1/5)-1 | D44: =('DCF'!$D$97/A44)^(1/7)-1 | E44: =('DCF'!$D$97/A44)^(1/10)-1 | F44: ='DCF'!$D$97
A45: ='Assumptions'!$B$8*(1+-0.2) | B45: =('DCF'!$D$97/A45)^(1/3)-1 | C45: =('DCF'!$D$97/A45)^(1/5)-1 | D45: =('DCF'!$D$97/A45)^(1/7)-1 | E45: =('DCF'!$D$97/A45)^(1/10)-1 | F45: ='DCF'!$D$97
A46: ='Assumptions'!$B$8*(1+-0.1) | B46: =('DCF'!$D$97/A46)^(1/3)-1 | C46: =('DCF'!$D$97/A46)^(1/5)-1 | D46: =('DCF'!$D$97/A46)^(1/7)-1 | E46: =('DCF'!$D$97/A46)^(1/10)-1 | F46: ='DCF'!$D$97
A47: ='Assumptions'!$B$8*(1+0.0) | B47: =('DCF'!$D$97/A47)^(1/3)-1 | C47: =('DCF'!$D$97/A47)^(1/5)-1 | D47: =('DCF'!$D$97/A47)^(1/7)-1 | E47: =('DCF'!$D$97/A47)^(1/10)-1 | F47: ='DCF'!$D$97
A48: ='Assumptions'!$B$8*(1+0.1) | B48: =('DCF'!$D$97/A48)^(1/3)-1 | C48: =('DCF'!$D$97/A48)^(1/5)-1 | D48: =('DCF'!$D$97/A48)^(1/7)-1 | E48: =('DCF'!$D$97/A48)^(1/10)-1 | F48: ='DCF'!$D$97
A49: ='Assumptions'!$B$8*(1+0.2) | B49: =('DCF'!$D$97/A49)^(1/3)-1 | C49: =('DCF'!$D$97/A49)^(1/5)-1 | D49: =('DCF'!$D$97/A49)^(1/7)-1 | E49: =('DCF'!$D$97/A49)^(1/10)-1 | F49: ='DCF'!$D$97
A50: ='Assumptions'!$B$8*(1+0.3) | B50: =('DCF'!$D$97/A50)^(1/3)-1 | C50: =('DCF'!$D$97/A50)^(1/5)-1 | D50: =('DCF'!$D$97/A50)^(1/7)-1 | E50: =('DCF'!$D$97/A50)^(1/10)-1 | F50: ='DCF'!$D$97
A52: Max entry for target IRR | B52: 3 yr | C52: 5 yr | D52: 7 yr | E52: 10 yr
A53: 10% IRR target | B53: ='DCF'!$D$97/(1+0.1)^3 | C53: ='DCF'!$D$97/(1+0.1)^5 | D53: ='DCF'!$D$97/(1+0.1)^7 | E53: ='DCF'!$D$97/(1+0.1)^10
A54: 15% IRR target | B54: ='DCF'!$D$97/(1+0.15)^3 | C54: ='DCF'!$D$97/(1+0.15)^5 | D54: ='DCF'!$D$97/(1+0.15)^7 | E54: ='DCF'!$D$97/(1+0.15)^10
A55: 20% IRR target | B55: ='DCF'!$D$97/(1+0.2)^3 | C55: ='DCF'!$D$97/(1+0.2)^5 | D55: ='DCF'!$D$97/(1+0.2)^7 | E55: ='DCF'!$D$97/(1+0.2)^10
A56: 25% IRR target | B56: ='DCF'!$D$97/(1+0.25)^3 | C56: ='DCF'!$D$97/(1+0.25)^5 | D56: ='DCF'!$D$97/(1+0.25)^7 | E56: ='DCF'!$D$97/(1+0.25)^10
A57: 30% IRR target | B57: ='DCF'!$D$97/(1+0.3)^3 | C57: ='DCF'!$D$97/(1+0.3)^5 | D57: ='DCF'!$D$97/(1+0.3)^7 | E57: ='DCF'!$D$97/(1+0.3)^10

Sheet Returns_Multiple
A1: RETURNS — Market Multiple Exit
A3: Approach: B — Market Multiple Exit
A4: Multiple chosen: EV/EBITDA on FY30. Rationale: Mature profitable cash-flow generator → EBITDA multiple
A6: Peer comps (linked from Assumptions)
A7: Peer | B7: EV/NTM Rev | C7: NTM Rev CAGR | D7: NTM EBITDA Margin | E7: EV/NTM EBITDA
A8: Peer A | B8: 4.2 | C8: 0.14 | D8: 0.22 | E8: 19
A9: Peer B | B9: 3.5 | C9: 0.1 | D9: 0.18 | E9: 16.5
A10: Peer C | B10: 5.1 | C10: 0.18 | D10: 0.25 | E10: 21
A11: Peer D | B11: 2.8 | C11: 0.08 | D11: 0.16 | E11: 14
A13: Exit multiple range
B14: Bear | C14: Base | D14: Bull
A15: Multiple (EV/EBITDA, FY30) | B15: ='Assumptions'!$B$58 | C15: ='Assumptions'!$C$58 | D15: ='Assumptions'!$D$58
A16: EBITDA (FY30) | B16: ='DCF'!$H$21 | C16: ='DCF'!$H$24 | D16: ='DCF'!$H$27
A17: Implied EV at exit | B17: =B16*B15 | C17: =C16*C15 | D17: =D16*D15
A18: + Net Cash | B18: ='Assumptions'!$B$10 | C18: ='Assumptions'!$B$10 | D18: ='Assumptions'!$B$10
A19: Implied Equity Value | B19: =B17+B18 | C19: =C17+C18 | D19: =D17+D18
A20: Implied Exit Price | B20: =B19/'Assumptions'!$B$9 | C20: =C19/'Assumptions'!$B$9 | D20: =D19/'Assumptions'!$B$9
A22: IRR sensitivity (Base scenario)
A23: Entry ↓ / Exit multiple → | B23: =C15*(1+-0.3) | C23: =C15*(1+-0.15) | D23: =C15*(1+0.0) | E23: =C15*(1+0.14999999999999997) | F23: =C15*(1+0.3)
A24: (holding period assumed: 5y)
A25: ='Assumptions'!$B$8*(1+-0.3) | B25: =((C16*$B$23+'Assumptions'!$B$10)/'Assumptions'!$B$9/A25)^(1/5)-1 | C25: =((C16*$C$23+'Assumptions'!$B$10)/'Assumptions'!$B$9/A25)^(1/5)-1 | D25: =((C16*$D$23+'Assumptions'!$B$10)/'Assumptions'!$B$9/A25)^(1/5)-1 | E25: =((C16*$E$23+'Assumptions'!$B$10)/'Assumptions'!$B$9/A25)^(1/5)-1 | F25: =((C16*$F$23+'Assumptions'!$B$10)/'Assumptions'!$B$9/A25)^(1/5)-1
A26: ='Assumptions'!$B$8*(1+-0.2) | B26: =((C16*$B$23+'Assumptions'!$B$10)/'Assumptions'!$B$9/A26)^(1/5)-1 | C26: =((C16*$C$23+'Assumptions'!$B$10)/'Assumptions'!$B$9/A26)^(1/5)-1 | D26: =((C16*$D$23+'Assumptions'!$B$10)/'Assumptions'!$B$9/A26)^(1/5)-1 | E26: =((C16*$E$23+'Assumptions'!$B$10)/'Assumptions'!$B$9/A26)^(1/5)-1 | F26: =((C16*$F$23+'Assumptions'!$B$10)/'Assumptions'!$B$9/A26)^(1/5)-1
A27: ='Assumptions'!$B$8*(1+-0.1) | B27: =((C16*$B$23+'Assumptions'!$B$10)/'Assumptions'!$B$9/A27)^(1/5)-1 | C27: =((C16*$C$23+'Assumptions'!$B$10)/'Assumptions'!$B$9/A27)^(1/5)-1 | D27: =((C16*$D$23+'Assumptions'!$B$10)/'Assumptions'!$B$9/A27)^(1/5)-1 | E27: =((C16*$E$23+'Assumptions'!$B$10)/'Assumptions'!$B$9/A27)^(1/5)-1 | F27: =((C16*$F$23+'Assumptions'!$B$10)/'Assumptions'!$B$9/A27)^(1/5)-1
A28: ='Assumptions'!$B$8*(1+0.0) | B28: =((C16*$B$23+'Assumptions'!$B$10)/'Assumptions'!$B$9/A28)^(1/5)-1 | C28: =((C16*$C$23+'Assumptions'!$B$10)/'Assumptions'!$B$9/A28)^(1/5)-1 | D28: =((C16*$D$23+'Assumptions'!$B$10)/'Assumptions'!$B$9/A28)^(1/5)-1 | E28: =((C16*$E$23+'Assumptions'!$B$10)/'Assumptions'!$B$9/A28)^(1/5)-1 | F28: =((C16*$F$23+'Assumptions'!$B$10)/'Assumptions'!$B$9/A28)^(1/5)-1
A29: ='Assumptions'!$B$8*(1+0.1) | B29: =((C16*$B$23+'Assumptions'!$B$10)/'Assumptions'!$B$9/A29)^(1/5)-1 | C29: =((C16*$C$23+'Assumptions'!$B$10)/'Assumptions'!$B$9/A29)^(1/5)-1 | D29: =((C16*$D$23+'Assumptions'!$B$10)/'Assumptions'!$B$9/A29)^(1/5)-1 | E29: =((C16*$E$23+'Assumptions'!$B$10)/'Assumptions'!$B$9/A29)^(1/5)-1 | F29: =((C16*$F$23+'Assumptions'!$B$10)/'Assumptions'!$B$9/A29)^(1/5)-1
A30: ='Assumptions'!$B$8*(1+0.2) | B30: =((C16*$B$23+'Assumptions'!$B$10)/'Assumptions'!$B$9/A30)^(1/5)-1 | C30: =((C16*$C$23+'Assumptions'!$B$10)/'Assumptions'!$B$9/A30)^(1/5)-1 | D30: =((C16*$D$23+'Assumptions'!$B$10)/'Assumptions'!$B$9/A30)^(1/5)-1 | E30: =((C16*$E$23+'Assumptions'!$B$10)/'Assumptions'!$B$9/A30)^(1/5)-1 | F30: =((C16*$F$23+'Assumptions'!$B$10)/'Assumptions'!$B$9/A30)^(1/5)-1
A31: ='Assumptions'!$B$8*(1+0.3) | B31: =((C16*$B$23+'Assumptions'!$B$10)/'Assumptions'!$B$9/A31)^(1/5)-1 | C31: =((C16*$C$23+'Assumptions'!$B$10)/'Assumptions'!$B$9/A31)^(1/5)-1 | D31: =((C16*$D$23+'Assumptions'!$B$10)/'Assumptions'!$B$9/A31)^(1/5)-1 | E31: =((C16*$E$23+'Assumptions'!$B$10)/'Assumptions'!$B$9/A31)^(1/5)-1 | F31: =((C16*$F$23+'Assumptions'!$B$10)/'Assumptions'!$B$9/A31)^(1/5)-1
A33: Max entry for target IRR (Base multiple)
A34: Target IRR → | B34: 10% | C34: 15% | D34: 20% | E34: 25% | F34: 30%
A35: Max entry (5y holding) | B35: =C20/(1+0.1)^5 | C35: =C20/(1+0.15)^5 | D35: =C20/(1+0.2)^5 | E35: =C20/(1+0.25)^5 | F35: =C20/(1+0.3)^5
A37: SYNTHESIS — Approach A (DCF) vs B (Multiple)
B38: Bear | C38: Base | D38: Bull
A39: A) DCF intrinsic price | B39: ='DCF'!$B$97 | C39: ='DCF'!$C$97 | D39: ='DCF'!$D$97
A40: B) Multiple-based exit price | B40: =B20 | C40: =C20 | D40: =D20
A41: Upside vs CMP — A | B41: =B39/'Assumptions'!$B$8-1 | C41: =C39/'Assumptions'!$B$8-1 | D41: =D39/'Assumptions'!$B$8-1
A42: Upside vs CMP — B | B42: =B40/'Assumptions'!$B$8-1 | C42: =C40/'Assumptions'!$B$8-1 | D42: =D40/'Assumptions'!$B$8-1
A43: IRR at CMP (assumes 5y holding) — A | B43: =(B39/'Assumptions'!$B$8)^(1/5)-1 | C43: =(C39/'Assumptions'!$B$8)^(1/5)-1 | D43: =(D39/'Assumptions'!$B$8)^(1/5)-1
A44: IRR at CMP (assumes 5y holding) — B | B44: =(B40/'Assumptions'!$B$8)^(1/5)-1 | C44: =(C40/'Assumptions'!$B$8)^(1/5)-1 | D44: =(D40/'Assumptions'!$B$8)^(1/5)-1
